textrpp_pu/__init__.py
textrpp_py-0.1.0.dist-info/licenses/LICENSE
textrpp_py-0.1.0.dist-info/METADATA
textrpp_py-0.1.0.dist-info/WHEEL
textrpp_py-0.1.0.dist-info/top_level.txt
textrpp_py-0.1.0.dist-info/RECORD
